[
  {
    "text": "Stay hungry, stay foolish.",
    "persona": "Steve Jobs",
    "tags": [
      "focus",
      "innovation"
    ],
    "source_url": "https://www.youtube.com/watch?v=UF8uR6Z6KLc",
    "retrieved_at": "2025-11-03T12:39:42.275595",
    "context": "Stanford commencement address, 2005"
  },
  {
    "text": "Everything negative \u2013 pressure, challenges \u2013 is an opportunity to rise.",
    "persona": "Kobe Bryant",
    "tags": [
      "perseverance",
      "grit"
    ],
    "source_url": "https://www.youtube.com/watch?v=5W-O2w-o9jo",
    "retrieved_at": "2025-11-03T12:39:42.275863"
  },
  {
    "text": "You must do the things you think you cannot do.",
    "persona": "Eleanor Roosevelt",
    "tags": [
      "courage",
      "self-belief"
    ],
    "source_url": "https://www.goodreads.com/quotes/58693",
    "retrieved_at": "2025-11-03T12:39:42.275867"
  },
  {
    "text": "Fear is the disease. Hustle is the antidote.",
    "persona": "Travis Kalanick",
    "tags": [
      "drive",
      "entrepreneurship"
    ],
    "source_url": "https://www.inc.com/magazine/201211/eric-markowitz/travis-kalanick-uber.html",
    "retrieved_at": "2025-11-03T12:39:42.275870"
  },
  {
    "text": "If I have seen further it is by standing on the shoulders of Giants.",
    "persona": "Isaac Newton",
    "tags": [
      "learning",
      "perseverance"
    ],
    "retrieved_at": "2025-11-04T17:04:32.878016"
  },
  {
    "text": "I am among those who think that science has great beauty.",
    "persona": "Marie Curie",
    "tags": [
      "learning"
    ],
    "retrieved_at": "2025-11-04T17:04:40.838391"
  },
  {
    "text": "The first principle is that you must not fool yourself \u2013 and you are the easiest person to fool.",
    "persona": "Richard Feynman",
    "tags": [
      "self-belief",
      "learning"
    ],
    "retrieved_at": "2025-11-04T17:04:48.435685"
  },
  {
    "text": "Somewhere, something incredible is waiting to be known.",
    "persona": "Carl Sagan",
    "tags": [
      "learning",
      "self-belief"
    ],
    "retrieved_at": "2025-11-04T17:04:59.650576"
  },
  {
    "text": "An expert is a person who has made all the mistakes that can be made in a very narrow field.",
    "persona": "Niels Bohr",
    "tags": [
      "learning",
      "perseverance"
    ],
    "retrieved_at": "2025-11-04T17:07:02.723640"
  },
  {
    "text": "I am among those who think that science has great beauty. A scientist in his laboratory is not only a technician: he is also a child facing natural phenomena that impress him as though they were fairy tales.",
    "persona": "Marie Curie",
    "tags": [
      "learning",
      "perseverance"
    ],
    "retrieved_at": "2025-11-05T08:33:50.673788"
  },
  {
    "text": "The only way to get better is to push yourself beyond your limits.",
    "persona": "David Goggins",
    "tags": [
      "perseverance",
      "discipline"
    ],
    "retrieved_at": "2025-11-05T08:44:47.415868"
  },
  {
    "text": "Discipline equals freedom.",
    "persona": "Jocko Willink",
    "tags": [
      "discipline",
      "self-belief"
    ],
    "retrieved_at": "2025-11-05T08:44:56.418976"
  },
  {
    "text": "I'm convinced that about half of what separates the successful entrepreneurs from the non-successful ones is pure perseverance.",
    "persona": "Steve Jobs",
    "tags": [
      "perseverance"
    ],
    "retrieved_at": "2025-11-05T08:45:05.047897"
  },
  {
    "text": "When something is important enough, you do it even if the odds are not in your favor.",
    "persona": "Elon Musk",
    "tags": [
      "perseverance",
      "self-belief"
    ],
    "source_url": "https://www.businessinsider.com/elon-musk-quotes-2015-2",
    "retrieved_at": "2025-11-05T08:45:14.184867"
  },
  {
    "text": "I am among those who think that science has great beauty. A scientist in his laboratory is not only a technician: he is also a child facing an experiment whose result will remain unknown.",
    "persona": "Marie Curie",
    "tags": [
      "learning",
      "perseverance"
    ],
    "retrieved_at": "2025-11-05T08:46:44.904612"
  },
  {
    "text": "The first principle is that you must not fool yourself\u2014and you are the easiest person to fool.",
    "persona": "Richard Feynman",
    "tags": [
      "self-belief",
      "learning"
    ],
    "retrieved_at": "2025-11-05T08:46:54.605192"
  },
  {
    "text": "I am among those who think that science has great beauty. A scientist in his laboratory is not only a technician: he is also a child facing natural phenomena with awe.",
    "persona": "Marie Curie",
    "tags": [
      "learning",
      "self-belief"
    ],
    "retrieved_at": "2025-11-05T08:49:32.564630"
  },
  {
    "text": "The only way to get to the other side is to go through it.",
    "persona": "David Goggins",
    "tags": [
      "perseverance",
      "discipline"
    ],
    "retrieved_at": "2025-11-05T08:53:42.245548"
  },
  {
    "text": "I am among those who think that science has great beauty. A scientist in his laboratory is not only a technician: he is also a child facing natural phenomena with awe and wonder.",
    "persona": "Marie Curie",
    "tags": [
      "learning",
      "perseverance"
    ],
    "retrieved_at": "2025-11-05T08:54:07.535941"
  },
  {
    "text": "You are not going to find your best self until you start to get uncomfortable.",
    "persona": "David Goggins",
    "tags": [
      "perseverance",
      "discipline"
    ],
    "retrieved_at": "2025-11-05T08:54:21.196649"
  },
  {
    "text": "You are not going to find a way to get through this without suffering. You have to embrace the pain and use it to fuel your fire.",
    "persona": "David Goggins",
    "tags": [
      "perseverance",
      "discipline"
    ],
    "retrieved_at": "2025-11-05T08:55:55.982229"
  },
  {
    "text": "I am among those who think that science has great beauty. A scientist in his laboratory is not only a technician: he is also a child facing an unknown world.",
    "persona": "Marie Curie",
    "tags": [
      "learning",
      "perseverance"
    ],
    "retrieved_at": "2025-11-05T08:56:15.074284"
  },
  {
    "text": "You are stopping you. You are giving up instead of getting hard.",
    "persona": "David Goggins",
    "tags": [
      "perseverance",
      "self-belief"
    ],
    "retrieved_at": "2025-11-05T10:36:45.182798"
  }
]